{
  "daisy": {
    "sys": {
      "colors": {
        "none": {
          "value": "rgba(255,255,255,0)",
          "type": "color"
        },
        "darken": {
          "hover": {
            "value": "0.13",
            "type": "number"
          },
          "active": {
            "value": "0.10",
            "type": "number"
          }
        },
        "opacity": {
          "disabled": {
            "bg": {
              "value": "0.3",
              "type": "number"
            },
            "content": {
              "value": "0.45",
              "type": "number"
            }
          },
          "hover": {
            "bg": {
              "value": "0.25",
              "type": "number"
            }
          },
          "backdrop": {
            "value": "0.3",
            "type": "number"
          }
        }
      }
    }
  }
}